MANIFEST.in
README.txt
setup.py
logistics/__init__.py
logistics/bootstrap_db.py
logistics/localsettings.py
logistics/localsettings.py.example
logistics/logistics.log
logistics/manage.py
logistics/settings.production.py
logistics/settings.py
logistics/settings.staging.py
logistics/urls.py
logistics/apps/__init__.py
logistics/apps/logistics/__init__.py
logistics/apps/logistics/admin.py
logistics/apps/logistics/app.py
logistics/apps/logistics/forms.py
logistics/apps/logistics/models.py
logistics/apps/logistics/schedule.py
logistics/apps/logistics/settings.py
logistics/apps/logistics/signals.py
logistics/apps/logistics/urls.py
logistics/apps/logistics/views.py
logistics/apps/logistics/extensions/__init__.py
logistics/apps/logistics/extensions/locations/__init__.py
logistics/apps/logistics/extensions/locations/location.py
logistics/apps/logistics/extensions/rapidsms/__init__.py
logistics/apps/logistics/extensions/rapidsms/contact.py
logistics/apps/logistics/fixtures/.initial_data.json.bak.swp
logistics/apps/logistics/fixtures/initial_data.json
logistics/apps/logistics/handlers/__init__.py
logistics/apps/logistics/handlers/codes.py
logistics/apps/logistics/handlers/help.py
logistics/apps/logistics/handlers/receipts.py
logistics/apps/logistics/handlers/stop.py
logistics/apps/logistics/locale/__init__.py
logistics/apps/logistics/locale/en/LC_MESSAGES/django.po
logistics/apps/logistics/static/images/minus.gif
logistics/apps/logistics/static/images/plus.gif
logistics/apps/logistics/static/images/sum.png
logistics/apps/logistics/static/javascripts/expand.js
logistics/apps/logistics/static/javascripts/jquery.flot.js
logistics/apps/logistics/static/javascripts/jquery.nestedAccordion.js
logistics/apps/logistics/static/stylesheets/logistics.css
logistics/apps/logistics/static/stylesheets/reports.css
logistics/apps/logistics/templates/logistics/aggregate.html
logistics/apps/logistics/templates/logistics/base.html
logistics/apps/logistics/templates/logistics/input_stock.html
sms_logistics.egg-info/PKG-INFO
sms_logistics.egg-info/SOURCES.txt
sms_logistics.egg-info/dependency_links.txt
sms_logistics.egg-info/top_level.txt