Metadata-Version: 1.0
Name: sms-logistics
Version: 0.0.1
Summary: Dimagi SMS Logistics
Home-page: http://www.dimagi.com/
Author: Dimagi
Author-email: information@dimagi.com
License: UNKNOWN
Platform: UNKNOWN
